{
  "recent_projects": [
    {
      "path": "X:\\GitHub\\PRJ-1",
      "name": "PRJ-1",
      "accessed_at": "2025-09-15T21:14:51.601641",
      "project_data": {}
    },
    {
      "path": "X:\\GitHub\\PySnoop",
      "name": "PySnoop",
      "accessed_at": "2025-09-15T21:11:36.897785",
      "project_data": {}
    },
    {
      "path": "X:\\GitHub\\NFC",
      "name": "NFC",
      "accessed_at": "2025-09-15T21:11:24.098023",
      "project_data": {}
    },
    {
      "path": "X:\\GitHub\\pass_mgr",
      "name": "pass_mgr",
      "accessed_at": "2025-09-15T21:11:14.321943",
      "project_data": {}
    },
    {
      "path": "X:\\GitHub\\credit_card_stripe_parser",
      "name": "credit_card_stripe_parser",
      "accessed_at": "2025-09-15T21:11:06.098597",
      "project_data": {}
    },
    {
      "path": "X:\\GitHub\\raspy_utility",
      "name": "raspy_utility",
      "accessed_at": "2025-09-15T21:10:57.265837",
      "project_data": {}
    },
    {
      "path": "X:\\GitHub\\MSR605",
      "name": "MSR605",
      "accessed_at": "2025-09-15T21:10:52.218046",
      "project_data": {}
    },
    {
      "path": "X:\\GitHub\\3D_Filament_Manager",
      "name": "3D_Filament_Manager",
      "accessed_at": "2025-09-15T21:10:47.610452",
      "project_data": {}
    },
    {
      "path": "X:\\GitHub\\CDE550-sim",
      "name": "CDE550-sim",
      "accessed_at": "2025-09-15T21:10:45.641762",
      "project_data": {}
    },
    {
      "path": "X:\\GitHub\\weather",
      "name": "weather",
      "accessed_at": "2025-09-15T21:10:43.962246",
      "project_data": {}
    },
    {
      "path": "X:\\GitHub\\Nidec_CommanderCDE",
      "name": "Nidec_CommanderCDE",
      "accessed_at": "2025-09-15T21:10:41.962275",
      "project_data": {}
    },
    {
      "path": "X:\\GitHub\\OpenPGP",
      "name": "OpenPGP",
      "accessed_at": "2025-09-15T21:10:11.553803",
      "project_data": {}
    },
    {
      "path": "X:\\GitHub\\nsfr750.github.io",
      "name": "nsfr750.github.io",
      "accessed_at": "2025-09-15T21:09:17.938584",
      "project_data": {}
    },
    {
      "path": "X:\\GitHub\\Onvif",
      "name": "Onvif",
      "accessed_at": "2025-09-15T21:09:16.843562",
      "project_data": {}
    },
    {
      "path": "X:\\GitHub\\benchmark",
      "name": "benchmark",
      "accessed_at": "2025-09-15T21:09:03.921917",
      "project_data": {}
    },
    {
      "path": "X:\\GitHub\\Images-Deduplicator",
      "name": "Images-Deduplicator",
      "accessed_at": "2025-09-15T01:20:03.371323",
      "project_data": {}
    },
    {
      "path": "X:\\GitHub\\EmailDuplicateCleaner",
      "name": "EmailDuplicateCleaner",
      "accessed_at": "2025-09-15T01:19:37.611018",
      "project_data": {}
    },
    {
      "path": "X:\\GitHub\\PDF_finder",
      "name": "PDF_finder",
      "accessed_at": "2025-09-15T01:19:25.171423",
      "project_data": {}
    },
    {
      "path": "X:\\GitHub\\3DViewer",
      "name": "3DViewer",
      "accessed_at": "2025-09-15T00:31:31.847399",
      "project_data": {}
    }
  ],
  "last_updated": "2025-09-15T21:14:51.602641"
}